convert2QRhead.py
setup.py
convert2QRhead.egg-info/PKG-INFO
convert2QRhead.egg-info/SOURCES.txt
convert2QRhead.egg-info/dependency_links.txt
convert2QRhead.egg-info/requires.txt
convert2QRhead.egg-info/top_level.txt