Metadata-Version: 1.0
Name: convert2QRhead
Version: 1.1
Summary: Convert your head portrait to QR code like head portrait. Written in Python
Home-page: https://github.com/YechengZhou/convert2QRhead
Author: YechengZhou
Author-email: ethanchou1126@gmail.com
License: BSD
Keywords: QR code,img
Platform: any
